AUTHORS.txt
CHANGELOG.txt
INSTALL.txt
LICENSE.txt
MANIFEST.in
README.md
setup.py
django_stw.egg-info/PKG-INFO
django_stw.egg-info/SOURCES.txt
django_stw.egg-info/dependency_links.txt
django_stw.egg-info/not-zip-safe
django_stw.egg-info/requires.txt
django_stw.egg-info/top_level.txt
stw/__init__.py
stw/models.py
stw/urls.py
stw/views.py
stw/templates/stwexample.html
stw/templatetags/__init__.py
stw/templatetags/shrinkthewebtags.py
stw/tests/__init__.py
stw/tests/test_templatetags.py