Metadata-Version: 1.1
Name: django-stw
Version: 1.0.1
Summary: This application provides templatetags for simplying using Shrink The Web PagePix
Home-page: https://github.com/saschwarz/django-stw
Author: Steve Schwarz
Author-email: steve@agilitynerd.com
License: UNKNOWN
Download-URL: https://github.com/saschwarz/django-stw/tarball/1.0.1
Keywords: Django,images,templatetag
Platform: UNKNOWN
Classifier: Development Status :: 5 - Production/Stable
Classifier: Environment :: Web Environment
Classifier: Intended Audience :: Developers
Classifier: License :: OSI Approved :: MIT License
Classifier: Operating System :: OS Independent
Classifier: Programming Language :: Python
Classifier: Framework :: Django
